{"state": "RI", "currency": "USD", "count": 2277, "params": {"brands": {}, "terpBreaks": [1.01, 1.01, 1.01, 1.01, 1.01, 1.01, 1.01, 1.01, 1.01, 1.01, 1.01, 1.01, 1.01, 1.01, 1.01, 1.01, 1.01, 1.01, 1.01, 1.01, 1.01], "weights": {"terp": 0.6, "cons": 0.4}, "gameAbove": [20, 25, 30], "impossible": 35}, "parts": 1, "dicts": {"s": ["dutchie:632e0f83b8f05a00bea6dce7", "dutchie:62be2003916c750095e616d5", "dutchie:63f65baa5e6022008c96eafb", "dutchie:68a4e39277f647100413a19e", "dutchie:6304f1dad20be000cf6d95bf"], "b": ["COAST Cannabis Co.", "Talaria", "420 Cannabis", "Willie's Reserve", "Newport Cannabis Co.", "Loud", "Hangar 420", "Hanks Herbs", "Firebrand", "Belushi Farms", "ODBC", "Sammy G's", "Tyson 2.0", "Herb", "Speakeasy Edibles", "ROVE", "Rhodies", "FESTIVAL", "Hangar Edibles", "T.F. Greens", "Cann Cure", "TetraZzz", "Rhode Island Reef", "Zen Blend Farms", "Sea Witch", "A-1 Herb Co", "Deep Green", "Lights Out", "Mary Janes", "Daily", "Del's", "Blazed", "RI Fully Grown", "Ocean State Curated Cannabis", "CMS Gardens", "Only Karts", "Jardin's Garden", "GreenMed Pros", "Fire Ganja", "Bayside Growers", "Infinite Bloom", "Vibez", "ELO", "Natural Green Choice", "Tier 401", "Coastal Farms", "East Coast Cultivation", "Growth Industries", "Constellations", "Livity", "Cultivating RI", "Aura of Rhode Island, Inc.", "House of Cultivar", "Ocean State Botanicals", "Stingers", "Bonsai Buds", "Elevated Supply", "Strikers", "Elz", "Highsman", "Salt Pond Pathways", "Moonstone Meds", "Green Angel", "Mammoth", "CMS", "Howls", "RI Cultivation Co.", "Nova Farms", "RI Finest Garden", "Zen Blend", "Smokies Edibles", "Sticky Fish", "OSCC", "Emerald Leaf Organics", "Hashables", "Zzzonked", "High Tides", "Gardening for Good", "Appalachian Distillery", "South County Cultivators", "Best Buds", "Lebeau & Joe's", "CanaHead", "Green Gruff", "Zen Pen", "Treetop Farms", "Pure Drip", "Daily Reserve", "Liberty Leave", "Sweetspot", "Rhody Reserve", "CannCure Cultivation", "Verde", "Belushi's Farm", "Canna Curious", "Airo", "Mammoth Inc", "Salt Pond", "Tyson", "RI Finest Gardens", "Plain Jane", "Headbangers", "Alpine Gold", "Lovewell Farms", "SeaWitch Medicinals", "Blitzzz'd", "Meltdown", "Highlands", "Sherlock Hemp Farms", "Evergreen", "Hydra Extracts", "Mother Earth Wellness", "Good Vibes", "Nebula", "Aquidneck Harvest Company", "Growers Reserve", "Catalyst", "Grassias", "Reborn Roots", "Jardins Gardens"], "c": ["Edible", "Flower", "Pre-Roll", "Vape", "Concentrate", "Topical", "Tincture", "Capsule", "Other"], "pt": ["Gummies", "Bud", "Single", "Disposable", "Infused", "Smalls", "Cartridge", "Chocolate", "Unspecified", "Hash", "Lotion/Cream", "Blunt", "Balm/Salve", "Sauce", "Shake/Trim", "Baked Goods", "RSO/Oil", "Badder/Budder", "Drink Mix", "Pack", "Kief", "Live Rosin", "Sugar", "Pod", "Rosin", "Capsule", "Distillate", "Hard Candy", "Diamonds", "Ground", "Mint", "Softgel", "Live Resin", "Crumble"], "t": ["Hybrid", "Indica", "Sativa", "CBD"], "sz": ["1g", "3.5g", "7g", "5g", "2g", "1.2g", "14g", "1.5g", ".1g", "0.01g", "2.5g", "0.0001g", "0.001g", ".15g", "1g / 2g", "16.1g", "0.004g", "N/A", "4g", "0.05g", "28g", "1.25g", "10g", "3.5g / 7g / 14g / 28g", "3g", "5.5g", "3.5g / 7g / 14g", "0.015g", "largeconcentrate", "0.26g", "3.5g / 7g", "75g", "0.02g", "edibles(10-10mgpieces)", "100mg", "1g / 5g", "3.5g / 14g", "0.5g", "375mg", "6g", "3.6g", "0.65g", "50mg", "10mg", "2g / 4g", "40mg", "8mg", "250mg", "150mg", "1.75g", "75mg", "2.75g", "0.7g", "5mgx20", "10mgx10", "0.3g", "4fl.oz", "120ml", "0.5fl.oz", "10mgx5", "25mgcbdx5mgcbn", "30ml", "1fl.oz", "1oz", "5x5mg", "10x5mg", "7floz", "1/8oz", "12fl.oz", "0.75g", "1flozperbottle", "2fl.oz", "25mgcbdx5mgcbg", "1.95g", "3.33g", ".5g", "0.85g"]}}